cmcp.py
cmcp-0.2.0.dist-info/METADATA
cmcp-0.2.0.dist-info/WHEEL
cmcp-0.2.0.dist-info/entry_points.txt
cmcp-0.2.0.dist-info/RECORD
