Metadata-Version: 2.1
Name: cmcp
Version: 0.2.0
Summary: A command-line utility for interacting with MCP servers.
Home-page: https://github.com/RussellLuo/cmcp
Author: RussellLuo
Author-email: luopeng.he@gmail.com
Requires-Python: >=3.10.0,<3.14
Classifier: Programming Language :: Python :: 3
Classifier: Programming Language :: Python :: 3.10
Classifier: Programming Language :: Python :: 3.11
Classifier: Programming Language :: Python :: 3.12
Requires-Dist: mcp (==1.8.0)
Requires-Dist: pygments (==2.19.1)
Project-URL: Repository, https://github.com/RussellLuo/cmcp
